django_sqs_extended_client/__init__.py
django_sqs_extended_client/apps.py
django_sqs_extended_client/aws/__init__.py
django_sqs_extended_client/aws/sns_client_extended.py
django_sqs_extended_client/event/__init__.py
django_sqs_extended_client/event/event_base.py
django_sqs_extended_client/event/event_base_aws.py
django_sqs_extended_client/event/event_dispatcher.py
django_sqs_extended_client/event/event_dispatcher_fifo.py
django_sqs_extended_client/event_processor/__init__.py
django_sqs_extended_client/event_processor/event_processor.py
django_sqs_extended_client/management/__init__.py
django_sqs_extended_client/management/commands/__init__.py
django_sqs_extended_client/management/commands/clean_s3_queues.py
django_sqs_extended_client/management/commands/process_queue.py
django_sqs_extended_client/queue/__init__.py
django_sqs_extended_client/queue/common.py
django_sqs_extended_client-2.6.1.dist-info/LICENSE
django_sqs_extended_client-2.6.1.dist-info/METADATA
django_sqs_extended_client-2.6.1.dist-info/WHEEL
django_sqs_extended_client-2.6.1.dist-info/top_level.txt
django_sqs_extended_client-2.6.1.dist-info/RECORD
