Metadata-Version: 2.1
Name: django-sqs-extended-client
Version: 2.6.1
Summary: A Django app to easily use AWS Simple Queue Service (SQS) with S3 for messages up to 2 GB.
Home-page: https://github.com/tommaso-castellani/django-sqs-extended-client
Author: Tommaso Castellani
Author-email: castellani.tom@gmail.com
License: MIT License
Classifier: Environment :: Other Environment
Classifier: Framework :: Django
Classifier: Framework :: Django :: 3.1
Classifier: Intended Audience :: Developers
Classifier: License :: OSI Approved :: MIT License
Classifier: Operating System :: OS Independent
Classifier: Programming Language :: Python
Classifier: Programming Language :: Python :: 3
Classifier: Programming Language :: Python :: 3 :: Only
Classifier: Programming Language :: Python :: 3.6
Classifier: Programming Language :: Python :: 3.7
License-File: LICENSE
Requires-Dist: django (>=3.1.5)
Requires-Dist: boto3 (>=1.16.56)
Requires-Dist: pytz (>=2021.1)
